xfox/__init__.py
xfox/__main__.py
xfox-0.1.9.6.dist-info/METADATA
xfox-0.1.9.6.dist-info/WHEEL
xfox-0.1.9.6.dist-info/RECORD
