Metadata-Version: 2.3
Name: xfox
Version: 0.1.9.6
Summary: Asynchronous Low-code compiler for python
Author: play-go
Author-email: ac248384@gmail.com
Requires-Python: >=3.10,<4.0
Classifier: Programming Language :: Python :: 3
Classifier: Programming Language :: Python :: 3.10
Classifier: Programming Language :: Python :: 3.11
Classifier: Programming Language :: Python :: 3.12
Classifier: Programming Language :: Python :: 3.13
Requires-Dist: nest-asyncio (>=1.6.0,<2.0.0)
